model/argument.py
model/operation.py
model/response.py
model/security.py
model/security_api_key.py
model/security_http_basic.py
model/security_http_bearer.py
model/security_o_auth.py
model/type_api.py
typeapi_model-0.1.1.dist-info/LICENSE
typeapi_model-0.1.1.dist-info/METADATA
typeapi_model-0.1.1.dist-info/WHEEL
typeapi_model-0.1.1.dist-info/top_level.txt
typeapi_model-0.1.1.dist-info/RECORD
